crypto_wealth_rank/__init__.py
crypto_wealth_rank/main.py
crypto_wealth_rank-0.1.0.dist-info/LICENSE
crypto_wealth_rank-0.1.0.dist-info/METADATA
crypto_wealth_rank-0.1.0.dist-info/WHEEL
crypto_wealth_rank-0.1.0.dist-info/top_level.txt
crypto_wealth_rank-0.1.0.dist-info/RECORD
