Metadata-Version: 2.1
Name: crypto-wealth-rank
Version: 0.1.0
Summary: A python package to get wealth rank depending on number of bitcoin/ethereum
Home-page: https://github.com/apinanyogaratnam/crypto-wealth-rank
Author: apinanyogaratnam
Author-email: apinanapinan@icloud.com
Classifier: Programming Language :: Python :: 3
Classifier: License :: OSI Approved :: MIT License
Classifier: Operating System :: OS Independent
Requires-Python: >=3.10.4
License-File: LICENSE
